prompete/__init__.py
prompete/chat.py
prompete/test_chat.py
prompete/tool_manager.py
Prompete-0.0.5.dist-info/LICENSE
Prompete-0.0.5.dist-info/METADATA
Prompete-0.0.5.dist-info/WHEEL
Prompete-0.0.5.dist-info/top_level.txt
Prompete-0.0.5.dist-info/RECORD
