Metadata-Version: 2.1
Name: Prompete
Version: 0.0.5
Summary: Prompting and templating
Author-email: Zbigniew Łukasiak <zbigniew@lukasiak.me>
License: MIT License
Project-URL: Homepage, https://github.com/zby/Prompete
Classifier: Programming Language :: Python :: 3
Classifier: License :: OSI Approved :: MIT License
Classifier: Operating System :: OS Independent
Requires-Python: >=3.10
License-File: LICENSE
Requires-Dist: wheel
Requires-Dist: pytest
Requires-Dist: LLMEasyTools>=0.25
Requires-Dist: setuptools>=61.0
Requires-Dist: pytest-mock
Requires-Dist: litellm
Requires-Dist: jinja2
